magento_dump/__init__.py
magento_dump/code_dump_utils.py
magento_dump/db_config.py
magento_dump/db_dump_utils.py
magento_dump/magento_dump.py
magento_dump/menu.py
magento_dump/table_utils.py
magento_dump-1.0.33.dist-info/METADATA
magento_dump-1.0.33.dist-info/WHEEL
magento_dump-1.0.33.dist-info/entry_points.txt
magento_dump-1.0.33.dist-info/top_level.txt
magento_dump-1.0.33.dist-info/RECORD
