Metadata-Version: 2.2
Name: magento-dump
Version: 1.0.33
Summary: Magento Database Code end Media Dump & Table Analyzer Tool
Home-page: https://github.com/genaker/magento-dump
Author: Yehor Shytikov
Author-email: egorshitikov@gmail.com
Classifier: Programming Language :: Python :: 3
Classifier: License :: OSI Approved :: MIT License
Classifier: Operating System :: OS Independent
Requires-Python: >=3.6
Requires-Dist: tqdm
Requires-Dist: simple-term-menu
Dynamic: author
Dynamic: author-email
Dynamic: classifier
Dynamic: description
Dynamic: description-content-type
Dynamic: home-page
Dynamic: requires-dist
Dynamic: requires-python
Dynamic: summary
